apkid/__init__.py
apkid/apkid.py
apkid/main.py
apkid/output.py
apkid/rules.py
apkid/rules/rules.yarc
ak_apkid-2.1.0.post1.dist-info/AUTHORS.txt
ak_apkid-2.1.0.post1.dist-info/LICENSE.COMMERCIAL
ak_apkid-2.1.0.post1.dist-info/LICENSE.GPL
ak_apkid-2.1.0.post1.dist-info/METADATA
ak_apkid-2.1.0.post1.dist-info/WHEEL
ak_apkid-2.1.0.post1.dist-info/entry_points.txt
ak_apkid-2.1.0.post1.dist-info/top_level.txt
ak_apkid-2.1.0.post1.dist-info/RECORD
