Metadata-Version: 2.1
Name: ak-apkid
Version: 2.1.0.post1
Summary: Android Package Identifier
Home-page: https://github.com/rednaga/APKiD
Author: Caleb Fenton & Tim Strazzere
Author-email: rednaga@protonmail.com
License: GPL & Commercial
Keywords: android analysis reversing malware apk dex dalvik
Platform: UNKNOWN
Classifier: Development Status :: 5 - Production/Stable
Classifier: Environment :: Console
Classifier: Intended Audience :: Science/Research
Classifier: License :: OSI Approved :: GNU General Public License v3 (GPLv3)
Classifier: License :: Other/Proprietary License
Classifier: Natural Language :: English
Classifier: Programming Language :: Python :: 3.6
Classifier: Programming Language :: Python :: 3.7
Classifier: Topic :: Security
Classifier: Topic :: Utilities
Requires-Dist: ak-yara-python (==3.11.0)
Provides-Extra: dev
Requires-Dist: mypy ; extra == 'dev'
Requires-Dist: pypandoc ; extra == 'dev'
Provides-Extra: test
Requires-Dist: delayed-assert ; extra == 'test'
Requires-Dist: factory-boy ; extra == 'test'
Requires-Dist: mock ; extra == 'test'
Requires-Dist: pytest ; extra == 'test'
Requires-Dist: pytest-cov ; extra == 'test'
Requires-Dist: pytest-factoryboy ; extra == 'test'
Requires-Dist: pytest-flask ; extra == 'test'
Requires-Dist: pytest-runner ; extra == 'test'
Requires-Dist: tox ; extra == 'test'
